EventTool-3.0.dist-info/METADATA
EventTool-3.0.dist-info/RECORD
EventTool-3.0.dist-info/WHEEL
EventTool-3.0.dist-info/top_level.txt
event/Event.py
event/EventClass.py
event/__init__.py
functions/DisplayFunctions.py
functions/Functions.py
functions/__init__.py
