Metadata-Version: 2.1
Name: EventTool
Version: 3.0
Summary: Package to process events in Calendar
Home-page: UNKNOWN
Author: Artur
Author-email: artur@wp.com
License: UNKNOWN
Platform: UNKNOWN
